streaming_assistants/__init__.py
streaming_assistants/patch.py
streaming_assistants-0.19.0.dist-info/METADATA
streaming_assistants-0.19.0.dist-info/WHEEL
streaming_assistants-0.19.0.dist-info/RECORD
