Metadata-Version: 2.1
Name: streaming-assistants
Version: 0.19.0
Summary: Streaming enabled Assistants API (deprecated in favor of astra-assistants)
Author: phact
Author-email: estevezsebastian@gmail.com
Requires-Python: >=3.10,<4.0
Classifier: Programming Language :: Python :: 3
Classifier: Programming Language :: Python :: 3.10
Classifier: Programming Language :: Python :: 3.11
Classifier: Programming Language :: Python :: 3.12
Requires-Dist: astra-assistants (>=2.0.0,<3.0.0)
